wheelchair/__init__.py
wheelchair/version.py
wheelchair/api/__init__.py
wheelchair/api/connection.py
wheelchair/api/exceptions.py
wheelchair/api/session.py
wheelchair/api/auth/__init__.py
wheelchair/api/auth/auth.py
wheelchair/api/auth/cookie_auth.py
wheelchair/api/cluster_setup/__init__.py
wheelchair/api/cluster_setup/cluster_setup.py
wheelchair/api/database/__init__.py
wheelchair/api/database/attachment.py
wheelchair/api/database/bulk.py
wheelchair/api/database/changes.py
wheelchair/api/database/database.py
wheelchair/api/database/design.py
wheelchair/api/database/doc.py
wheelchair/api/database/index.py
wheelchair/api/database/partition.py
wheelchair/api/database/purged_infos_limit.py
wheelchair/api/database/revs_limit.py
wheelchair/api/database/search.py
wheelchair/api/database/security.py
wheelchair/api/database/shards.py
wheelchair/api/database/update.py
wheelchair/api/database/view.py
wheelchair/api/node/__init__.py
wheelchair/api/node/config.py
wheelchair/api/node/node.py
wheelchair/api/scheduler/__init__.py
wheelchair/api/scheduler/scheduler.py
wheelchair/api/server/__init__.py
wheelchair/api/server/server.py
wheelchair/api/utils/__init__.py
wheelchair/api/utils/query.py
wheelchair/api/utils/raw_collation.py
wheelchair/api/utils/simple_scope.py
wheelchair/api/utils/stale_options.py
wheelchair-0.1.10.dist-info/LICENSE
wheelchair-0.1.10.dist-info/METADATA
wheelchair-0.1.10.dist-info/WHEEL
wheelchair-0.1.10.dist-info/top_level.txt
wheelchair-0.1.10.dist-info/RECORD
